boondmanager/__init__.py
boondmanager/__version__.py
boondmanager/auth.py
boondmanager/exceptions.py
boondmanager/utils.py
boondmanager/api/__init__.py
boondmanager/api/absences.py
boondmanager/api/absences_reports.py
boondmanager/api/accounts.py
boondmanager/api/actions.py
boondmanager/api/administrator.py
boondmanager/api/advantages.py
boondmanager/api/agencies.py
boondmanager/api/application.py
boondmanager/api/attached_flags.py
boondmanager/api/base.py
boondmanager/api/billing.py
boondmanager/api/business_units.py
boondmanager/api/calendars.py
boondmanager/api/candidates.py
boondmanager/api/charts.py
boondmanager/api/companies.py
boondmanager/api/contacts.py
boondmanager/api/contracts.py
boondmanager/api/dashboard.py
boondmanager/api/deliveries.py
boondmanager/api/devices.py
boondmanager/api/documents.py
boondmanager/api/esignature.py
boondmanager/api/expenses.py
boondmanager/api/flags.py
boondmanager/api/forms.py
boondmanager/api/groupments.py
boondmanager/api/imports.py
boondmanager/api/inactivities.py
boondmanager/api/invoices.py
boondmanager/api/logs.py
boondmanager/api/marketplace.py
boondmanager/api/opportunities.py
boondmanager/api/orders.py
boondmanager/api/payments.py
boondmanager/api/poles.py
boondmanager/api/positionings.py
boondmanager/api/products.py
boondmanager/api/projects.py
boondmanager/api/purchases.py
boondmanager/api/reporting.py
boondmanager/api/resources.py
boondmanager/api/roles.py
boondmanager/api/sandbox.py
boondmanager/api/savedsearches.py
boondmanager/api/share.py
boondmanager/api/signatures.py
boondmanager/api/subscription.py
boondmanager/api/targets.py
boondmanager/api/tasks.py
boondmanager/api/thread.py
boondmanager/api/thumbnails.py
boondmanager/api/times.py
boondmanager/api/times_reports.py
boondmanager/api/todolists.py
boondmanager/api/validations.py
boondmanager/api/vendor.py
boondmanager/api/webhooks.py
boondmanager/api/workplaces_times.py
tests/__init__.py
tests/test_auth.py
tests/test_clients.py
tests/test_utils.py
pyboondmanager-0.0.1.dist-info/LICENSE
pyboondmanager-0.0.1.dist-info/METADATA
pyboondmanager-0.0.1.dist-info/WHEEL
pyboondmanager-0.0.1.dist-info/top_level.txt
pyboondmanager-0.0.1.dist-info/RECORD
