Metadata-Version: 2.1
Name: pyboondmanager
Version: 0.0.1
Summary: Python connector for BoondManager
Home-page: https://github.com/tominardi/pyboondmanager
Author: Thomas Durey
Author-email: tominardi@gmail.com
License: Apache License, Version 2.0
Keywords: api,erp,esn,boondmanager,integration,project management,resource management,automation,productivity,professional services,business solution
Classifier: Development Status :: 3 - Alpha
Classifier: Intended Audience :: Developers
Classifier: License :: OSI Approved :: Apache Software License
Classifier: Operating System :: OS Independent
Classifier: Programming Language :: Python :: 3
Classifier: Programming Language :: Python :: 3.7
Classifier: Programming Language :: Python :: 3.8
Classifier: Programming Language :: Python :: 3.9
Classifier: Programming Language :: Python :: 3.10
Classifier: Topic :: Software Development :: Libraries :: Python Modules
License-File: LICENSE
